repo_gist_sync/__init__.py
repo_gist_sync/cli.py
repo_gist_sync/repo_gist_sync.py
repo_gist_sync-0.4.5.dist-info/LICENSE
repo_gist_sync-0.4.5.dist-info/METADATA
repo_gist_sync-0.4.5.dist-info/WHEEL
repo_gist_sync-0.4.5.dist-info/entry_points.txt
repo_gist_sync-0.4.5.dist-info/top_level.txt
repo_gist_sync-0.4.5.dist-info/zip-safe
repo_gist_sync-0.4.5.dist-info/RECORD
