Metadata-Version: 2.1
Name: repo-gist-sync
Version: 0.4.5
Summary: Library to sync git repository to Github Gists
Home-page: https://github.com/weeping-angel/repo-gist-sync
Author: Nishu Jain
Author-email: nishujain1997.19@gmail.com
License: MIT
Platform: unix
Platform: linux
Platform: osx
Platform: win32
Platform: cygwin
Classifier: Development Status :: 5 - Production/Stable
Classifier: Intended Audience :: Developers
Classifier: License :: OSI Approved :: MIT License
Classifier: Natural Language :: English
Classifier: Programming Language :: Python :: 3
Classifier: Programming Language :: Python :: 3 :: Only
Classifier: Programming Language :: Python :: 3.6
Classifier: Programming Language :: Python :: 3.7
Classifier: Programming Language :: Python :: 3.8
Classifier: Programming Language :: Python :: 3.9
Requires-Python: >=3.6
License-File: LICENSE
Requires-Dist: requests
Requires-Dist: click
